pystandalonehtml/__init__.py
pystandalonehtml/cli.py
pystandalonehtml/converter.py
pystandalonehtml-0.1.10.dist-info/AUTHORS.rst
pystandalonehtml-0.1.10.dist-info/LICENSE
pystandalonehtml-0.1.10.dist-info/METADATA
pystandalonehtml-0.1.10.dist-info/WHEEL
pystandalonehtml-0.1.10.dist-info/entry_points.txt
pystandalonehtml-0.1.10.dist-info/top_level.txt
pystandalonehtml-0.1.10.dist-info/RECORD
